{
  "url": "https://github.com/Enterprise-CMCS/macpro-mdct-qmr",
  "owner": "Enterprise-CMCS",
  "name": "macpro-mdct-qmr",
  "description": "QMR is the CMCS MDCT application for collecting state data for related to measuring and quantifying healthcare processes and ensuring quality healthcare for Medicaid beneficiaries. The collected data assists CMCS in monitoring, managing, and better understanding Medicaid and CHIP programs.",
  "commits_count": 4717,
  "issues_count": 0,
  "open_issues_count": 0,
  "closed_issues_count": 0,
  "pull_requests_count": 1980,
  "open_pull_requests_count": 3,
  "merged_pull_requests_count": 1680,
  "closed_pull_requests_count": 297,
  "forks_count": 0,
  "stargazers_count": 3,
  "watchers_count": 11,
  "total_project_lines": 216564,
  "average_project_lines": 105,
  "total_project_comment_lines": 5689,
  "average_project_comment_lines": 3,
  "total_project_blank_lines": 15262,
  "average_blank_lines": 7,
  "commits_by_month": {
    "2025/6": 11,
    "2025/5": 19
  },
  "new_commit_contributors_by_day_over_last_month": [],
  "new_commit_contributors_by_day_over_last_six_months": [],
  "new_issues_by_day_over_last_month": [],
  "new_issues_by_day_over_last_six_months": [],
  "nadia_shields_badge_url": "https://img.shields.io/static/v1?label=project+type&message=midsize&color=ff0000",
  "nadia_color": "ff0000",
  "nadia_badge_name": "midsize",
  "created_at": "2021-02-25T16:57:16Z",
  "ossf_scorecard": {
    "date": "2025-06-22T14:40:31Z",
    "repo": {
      "name": "github.com/Enterprise-CMCS/macpro-mdct-qmr",
      "commit": "a4cb8ebf9a3db0818590a21dcfeed97971f629a0"
    },
    "scorecard": {
      "version": "v5.1.1-45-g40bbc9c9",
      "commit": "40bbc9c958aa66327fb026b2136f1951298ca0f8"
    },
    "score": 5.1,
    "checks": [
      {
        "details": null,
        "score": 10,
        "reason": "no binaries found in the repo",
        "name": "Binary-Artifacts",
        "documentation": {
          "url": "https://github.com/ossf/scorecard/blob/40bbc9c958aa66327fb026b2136f1951298ca0f8/docs/checks.md#binary-artifacts",
          "short": "Determines if the project has generated executable (binary) artifacts in the source repository."
        }
      },
      {
        "details": null,
        "score": 8,
        "reason": "branch protection is not maximal on development and all release branches",
        "name": "Branch-Protection",
        "documentation": {
          "url": "https://github.com/ossf/scorecard/blob/40bbc9c958aa66327fb026b2136f1951298ca0f8/docs/checks.md#branch-protection",
          "short": "Determines if the default and release branches are protected with GitHub's branch protection settings."
        }
      },
      {
        "details": null,
        "score": 9,
        "reason": "29 out of 30 merged PRs checked by a CI test -- score normalized to 9",
        "name": "CI-Tests",
        "documentation": {
          "url": "https://github.com/ossf/scorecard/blob/40bbc9c958aa66327fb026b2136f1951298ca0f8/docs/checks.md#ci-tests",
          "short": "Determines if the project runs tests before pull requests are merged."
        }
      },
      {
        "details": null,
        "score": 0,
        "reason": "no effort to earn an OpenSSF best practices badge detected",
        "name": "CII-Best-Practices",
        "documentation": {
          "url": "https://github.com/ossf/scorecard/blob/40bbc9c958aa66327fb026b2136f1951298ca0f8/docs/checks.md#cii-best-practices",
          "short": "Determines if the project has an OpenSSF (formerly CII) Best Practices Badge."
        }
      },
      {
        "details": null,
        "score": 10,
        "reason": "all changesets reviewed",
        "name": "Code-Review",
        "documentation": {
          "url": "https://github.com/ossf/scorecard/blob/40bbc9c958aa66327fb026b2136f1951298ca0f8/docs/checks.md#code-review",
          "short": "Determines if the project requires human code review before pull requests (aka merge requests) are merged."
        }
      },
      {
        "details": null,
        "score": 10,
        "reason": "project has 6 contributing companies or organizations",
        "name": "Contributors",
        "documentation": {
          "url": "https://github.com/ossf/scorecard/blob/40bbc9c958aa66327fb026b2136f1951298ca0f8/docs/checks.md#contributors",
          "short": "Determines if the project has a set of contributors from multiple organizations (e.g., companies)."
        }
      },
      {
        "details": null,
        "score": 0,
        "reason": "dangerous workflow patterns detected",
        "name": "Dangerous-Workflow",
        "documentation": {
          "url": "https://github.com/ossf/scorecard/blob/40bbc9c958aa66327fb026b2136f1951298ca0f8/docs/checks.md#dangerous-workflow",
          "short": "Determines if the project's GitHub Action workflows avoid dangerous patterns."
        }
      },
      {
        "details": null,
        "score": 10,
        "reason": "update tool detected",
        "name": "Dependency-Update-Tool",
        "documentation": {
          "url": "https://github.com/ossf/scorecard/blob/40bbc9c958aa66327fb026b2136f1951298ca0f8/docs/checks.md#dependency-update-tool",
          "short": "Determines if the project uses a dependency update tool."
        }
      },
      {
        "details": null,
        "score": 0,
        "reason": "project is not fuzzed",
        "name": "Fuzzing",
        "documentation": {
          "url": "https://github.com/ossf/scorecard/blob/40bbc9c958aa66327fb026b2136f1951298ca0f8/docs/checks.md#fuzzing",
          "short": "Determines if the project uses fuzzing."
        }
      },
      {
        "details": null,
        "score": 9,
        "reason": "license file detected",
        "name": "License",
        "documentation": {
          "url": "https://github.com/ossf/scorecard/blob/40bbc9c958aa66327fb026b2136f1951298ca0f8/docs/checks.md#license",
          "short": "Determines if the project has defined a license."
        }
      },
      {
        "details": null,
        "score": 10,
        "reason": "30 commit(s) and 0 issue activity found in the last 90 days -- score normalized to 10",
        "name": "Maintained",
        "documentation": {
          "url": "https://github.com/ossf/scorecard/blob/40bbc9c958aa66327fb026b2136f1951298ca0f8/docs/checks.md#maintained",
          "short": "Determines if the project is \"actively maintained\"."
        }
      },
      {
        "details": null,
        "score": -1,
        "reason": "packaging workflow not detected",
        "name": "Packaging",
        "documentation": {
          "url": "https://github.com/ossf/scorecard/blob/40bbc9c958aa66327fb026b2136f1951298ca0f8/docs/checks.md#packaging",
          "short": "Determines if the project is published as a package that others can easily download, install, easily update, and uninstall."
        }
      },
      {
        "details": null,
        "score": 0,
        "reason": "dependency not pinned by hash detected -- score normalized to 0",
        "name": "Pinned-Dependencies",
        "documentation": {
          "url": "https://github.com/ossf/scorecard/blob/40bbc9c958aa66327fb026b2136f1951298ca0f8/docs/checks.md#pinned-dependencies",
          "short": "Determines if the project has declared and pinned the dependencies of its build process."
        }
      },
      {
        "details": null,
        "score": 9,
        "reason": "SAST tool detected but not run on all commits",
        "name": "SAST",
        "documentation": {
          "url": "https://github.com/ossf/scorecard/blob/40bbc9c958aa66327fb026b2136f1951298ca0f8/docs/checks.md#sast",
          "short": "Determines if the project uses static code analysis."
        }
      },
      {
        "details": null,
        "score": 0,
        "reason": "security policy file not detected",
        "name": "Security-Policy",
        "documentation": {
          "url": "https://github.com/ossf/scorecard/blob/40bbc9c958aa66327fb026b2136f1951298ca0f8/docs/checks.md#security-policy",
          "short": "Determines if the project has published a security policy."
        }
      },
      {
        "details": null,
        "score": -1,
        "reason": "no releases found",
        "name": "Signed-Releases",
        "documentation": {
          "url": "https://github.com/ossf/scorecard/blob/40bbc9c958aa66327fb026b2136f1951298ca0f8/docs/checks.md#signed-releases",
          "short": "Determines if the project cryptographically signs release artifacts."
        }
      },
      {
        "details": null,
        "score": 0,
        "reason": "detected GitHub workflow tokens with excessive permissions",
        "name": "Token-Permissions",
        "documentation": {
          "url": "https://github.com/ossf/scorecard/blob/40bbc9c958aa66327fb026b2136f1951298ca0f8/docs/checks.md#token-permissions",
          "short": "Determines if the project's workflows follow the principle of least privilege."
        }
      },
      {
        "details": null,
        "score": 0,
        "reason": "22 existing vulnerabilities detected",
        "name": "Vulnerabilities",
        "documentation": {
          "url": "https://github.com/ossf/scorecard/blob/40bbc9c958aa66327fb026b2136f1951298ca0f8/docs/checks.md#vulnerabilities",
          "short": "Determines if the project has open, known unfixed vulnerabilities."
        }
      }
    ],
    "metadata": null
  },
  "cocomo": {
    "languageSummary": [
      {
        "Name": "TypeScript",
        "Bytes": 4047443,
        "CodeBytes": 0,
        "Lines": 127338,
        "Code": 114941,
        "Comment": 3514,
        "Blank": 8883,
        "Complexity": 5623,
        "Count": 1451,
        "WeightedComplexity": 0,
        "Files": [],
        "LineLength": null,
        "ULOC": 0
      },
      {
        "Name": "JSON",
        "Bytes": 47544,
        "CodeBytes": 0,
        "Lines": 2018,
        "Code": 2018,
        "Comment": 0,
        "Blank": 0,
        "Complexity": 0,
        "Count": 21,
        "WeightedComplexity": 0,
        "Files": [],
        "LineLength": null,
        "ULOC": 0
      },
      {
        "Name": "JavaScript",
        "Bytes": 39404,
        "CodeBytes": 0,
        "Lines": 1264,
        "Code": 888,
        "Comment": 224,
        "Blank": 152,
        "Complexity": 37,
        "Count": 21,
        "WeightedComplexity": 0,
        "Files": [],
        "LineLength": null,
        "ULOC": 0
      },
      {
        "Name": "YAML",
        "Bytes": 33489,
        "CodeBytes": 0,
        "Lines": 949,
        "Code": 861,
        "Comment": 21,
        "Blank": 67,
        "Complexity": 0,
        "Count": 17,
        "WeightedComplexity": 0,
        "Files": [],
        "LineLength": null,
        "ULOC": 0
      },
      {
        "Name": "Markdown",
        "Bytes": 46029,
        "CodeBytes": 0,
        "Lines": 1053,
        "Code": 683,
        "Comment": 0,
        "Blank": 370,
        "Complexity": 0,
        "Count": 9,
        "WeightedComplexity": 0,
        "Files": [],
        "LineLength": null,
        "ULOC": 0
      },
      {
        "Name": "Shell",
        "Bytes": 11118,
        "CodeBytes": 0,
        "Lines": 360,
        "Code": 252,
        "Comment": 39,
        "Blank": 69,
        "Complexity": 63,
        "Count": 9,
        "WeightedComplexity": 0,
        "Files": [],
        "LineLength": null,
        "ULOC": 0
      },
      {
        "Name": "SVG",
        "Bytes": 366107,
        "CodeBytes": 0,
        "Lines": 117,
        "Code": 117,
        "Comment": 0,
        "Blank": 0,
        "Complexity": 0,
        "Count": 7,
        "WeightedComplexity": 0,
        "Files": [],
        "LineLength": null,
        "ULOC": 0
      },
      {
        "Name": "TypeScript Typings",
        "Bytes": 3388,
        "CodeBytes": 0,
        "Lines": 105,
        "Code": 57,
        "Comment": 24,
        "Blank": 24,
        "Complexity": 4,
        "Count": 5,
        "WeightedComplexity": 0,
        "Files": [],
        "LineLength": null,
        "ULOC": 0
      },
      {
        "Name": "Plain Text",
        "Bytes": 5436,
        "CodeBytes": 0,
        "Lines": 28,
        "Code": 25,
        "Comment": 0,
        "Blank": 3,
        "Complexity": 0,
        "Count": 4,
        "WeightedComplexity": 0,
        "Files": [],
        "LineLength": null,
        "ULOC": 0
      },
      {
        "Name": "HTML",
        "Bytes": 2909,
        "CodeBytes": 0,
        "Lines": 87,
        "Code": 84,
        "Comment": 2,
        "Blank": 1,
        "Complexity": 0,
        "Count": 2,
        "WeightedComplexity": 0,
        "Files": [],
        "LineLength": null,
        "ULOC": 0
      },
      {
        "Name": "Sass",
        "Bytes": 22833,
        "CodeBytes": 0,
        "Lines": 654,
        "Code": 626,
        "Comment": 3,
        "Blank": 25,
        "Complexity": 0,
        "Count": 2,
        "WeightedComplexity": 0,
        "Files": [],
        "LineLength": null,
        "ULOC": 0
      },
      {
        "Name": "BASH",
        "Bytes": 2870,
        "CodeBytes": 0,
        "Lines": 94,
        "Code": 66,
        "Comment": 12,
        "Blank": 16,
        "Complexity": 14,
        "Count": 1,
        "WeightedComplexity": 0,
        "Files": [],
        "LineLength": null,
        "ULOC": 0
      },
      {
        "Name": "CloudFormation (YAML)",
        "Bytes": 20757,
        "CodeBytes": 0,
        "Lines": 568,
        "Code": 526,
        "Comment": 42,
        "Blank": 0,
        "Complexity": 63,
        "Count": 1,
        "WeightedComplexity": 0,
        "Files": [],
        "LineLength": null,
        "ULOC": 0
      },
      {
        "Name": "Smarty Template",
        "Bytes": 895,
        "CodeBytes": 0,
        "Lines": 18,
        "Code": 14,
        "Comment": 0,
        "Blank": 4,
        "Complexity": 0,
        "Count": 1,
        "WeightedComplexity": 0,
        "Files": [],
        "LineLength": null,
        "ULOC": 0
      },
      {
        "Name": "TOML",
        "Bytes": 39,
        "CodeBytes": 0,
        "Lines": 2,
        "Code": 2,
        "Comment": 0,
        "Blank": 0,
        "Complexity": 0,
        "Count": 1,
        "WeightedComplexity": 0,
        "Files": [],
        "LineLength": null,
        "ULOC": 0
      },
      {
        "Name": "XML",
        "Bytes": 326,
        "CodeBytes": 0,
        "Lines": 11,
        "Code": 11,
        "Comment": 0,
        "Blank": 0,
        "Complexity": 0,
        "Count": 1,
        "WeightedComplexity": 0,
        "Files": [],
        "LineLength": null,
        "ULOC": 0
      }
    ],
    "estimatedCost_low": 3794288.5943341623,
    "estimatedScheduleMonths_low": 23.642661190880794,
    "estimatedPeople_low": 15.634482464217081,
    "estimatedCost_high": 11824660.433453366,
    "estimatedScheduleMonths_high": 23.642661190880794,
    "estimatedPeople_high": 15.634482464217081,
    "dryness_table": "───────────────────────────────────────────────────────────────────────────────\nLanguage                 Files     Lines   Blanks  Comments     Code Complexity\n───────────────────────────────────────────────────────────────────────────────\nTypeScript                1451    127338     8883      3514   114941       5623\n(ULOC)                             26111\n-------------------------------------------------------------------------------\nJSON                        21      2018        0         0     2018          0\n(ULOC)                               743\n-------------------------------------------------------------------------------\nJavaScript                  21      1264      152       224      888         37\n(ULOC)                               771\n-------------------------------------------------------------------------------\nYAML                        17       949       67        21      861          0\n(ULOC)                               523\n-------------------------------------------------------------------------------\nMarkdown                     9      1053      370         0      683          0\n(ULOC)                               575\n-------------------------------------------------------------------------------\nShell                        9       360       69        39      252         63\n(ULOC)                               234\n-------------------------------------------------------------------------------\nSVG                          7       117        0         0      117          0\n(ULOC)                               109\n-------------------------------------------------------------------------------\nTypeScript Typings           5       105       24        24       57          4\n(ULOC)                                75\n-------------------------------------------------------------------------------\nPlain Text                   4        28        3         0       25          0\n(ULOC)                                22\n-------------------------------------------------------------------------------\nHTML                         2        87        1         2       84          0\n(ULOC)                                69\n-------------------------------------------------------------------------------\nSass                         2       654       25         3      626          0\n(ULOC)                               599\n-------------------------------------------------------------------------------\nBASH                         1        94       16        12       66         14\n(ULOC)                                62\n-------------------------------------------------------------------------------\nCloudFormation (YAM…         1       568        0        42      526         63\n(ULOC)                               363\n-------------------------------------------------------------------------------\nSmarty Template              1        18        4         0       14          0\n(ULOC)                                15\n-------------------------------------------------------------------------------\nTOML                         1         2        0         0        2          0\n(ULOC)                                 2\n-------------------------------------------------------------------------------\nXML                          1        11        0         0       11          0\n(ULOC)                                11\n───────────────────────────────────────────────────────────────────────────────\nTotal                     1553    134666     9614      3881   121171       5804\n───────────────────────────────────────────────────────────────────────────────\nUnique Lines of Code (ULOC)        30165\nDRYness %                           0.22\n───────────────────────────────────────────────────────────────────────────────\nEstimated Cost to Develop (organic) $4,160,676\nEstimated Schedule Effort (organic) 23.64 months\nEstimated People Required (organic) 15.63\n───────────────────────────────────────────────────────────────────────────────\nProcessed 4650587 bytes, 4.651 megabytes (SI)\n───────────────────────────────────────────────────────────────────────────────\n"
  },
  "predominant_langs": {
    "TypeScript": 4041095,
    "JavaScript": 45752,
    "SCSS": 22833,
    "Shell": 4029,
    "HTML": 2909,
    "Smarty": 895
  },
  "average_issue_resolution_time": [],
  "repo_dependency_libyear_list": [
    [
      "aws-sdk",
      0.0,
      "2024-03-11T01:24:26.000"
    ],
    [
      "cypress",
      1.8410958904,
      "2023-08-29T18:14:22.000"
    ],
    [
      "cypress-file-upload",
      0.0,
      "2023-08-29T18:14:22.000"
    ],
    [
      "cypress-image-snapshot",
      0.0,
      "2023-08-29T18:14:22.000"
    ],
    [
      "cypress-tests",
      -1.0,
      "2023-10-22T07:03:03.000"
    ],
    [
      "cypress-xpath",
      0.0821917808,
      "2023-08-29T18:14:22.000"
    ],
    [
      "dotenv",
      2.1178082192,
      "2023-10-22T07:03:03.000"
    ],
    [
      "dotenv",
      2.7945205479,
      "2024-04-13T02:28:05.000"
    ],
    [
      "dotenv",
      3.5835616438,
      "2025-04-09T00:28:53.000"
    ],
    [
      "@enterprise-cmcs/serverless-waf-plugin",
      0.0,
      "2025-04-09T00:28:53.000"
    ],
    [
      "eslint",
      2.0684931507,
      "2023-08-29T18:14:22.000"
    ],
    [
      "eslint",
      2.2219178082,
      "2023-10-22T07:03:03.000"
    ],
    [
      "eslint",
      2.5671232877,
      "2024-03-11T01:24:26.000"
    ],
    [
      "eslint",
      2.6821917808,
      "2024-04-13T02:28:05.000"
    ],
    [
      "eslint",
      3.6794520548,
      "2025-04-09T00:28:53.000"
    ],
    [
      "eslint-config-airbnb",
      1.1315068493,
      "2025-04-09T00:28:53.000"
    ],
    [
      "eslint-plugin-import",
      0.0,
      "2025-04-09T00:28:53.000"
    ],
    [
      "eslint-plugin-jsx-a11y",
      0.0,
      "2025-04-09T00:28:53.000"
    ],
    [
      "eslint-plugin-react",
      0.0,
      "2025-04-09T00:28:53.000"
    ],
    [
      "eslint-plugin-react-hooks",
      0.0,
      "2025-04-09T00:28:53.000"
    ],
    [
      "prettier",
      0.3506849315,
      "2023-10-22T07:03:03.000"
    ],
    [
      "prettier",
      0.7835616438,
      "2024-04-13T02:28:05.000"
    ],
    [
      "prettier",
      1.8602739726,
      "2025-04-09T00:28:53.000"
    ],
    [
      "serverless",
      -0.3260273973,
      "2024-04-13T02:28:05.000"
    ],
    [
      "serverless",
      -0.2712328767,
      "2024-03-11T01:24:26.000"
    ],
    [
      "serverless",
      -0.0273972603,
      "2023-10-22T07:03:03.000"
    ],
    [
      "serverless",
      0.0,
      "2023-08-29T18:14:22.000"
    ],
    [
      "serverless",
      0.304109589,
      "2025-04-09T00:28:53.000"
    ],
    [
      "serverless-bundle",
      0.0,
      "2025-04-09T00:28:53.000"
    ],
    [
      "@serverless/compose",
      0.0,
      "2025-04-09T00:28:53.000"
    ],
    [
      "serverless-dotenv-plugin",
      0.6273972603,
      "2025-04-09T00:28:53.000"
    ],
    [
      "serverless-iam-helper",
      0.0,
      "2025-04-09T00:28:53.000"
    ],
    [
      "serverless-idempotency-helper",
      0.0,
      "2024-04-13T02:28:05.000"
    ],
    [
      "serverless-offline",
      0.0,
      "2025-04-09T00:28:53.000"
    ],
    [
      "serverless-offline",
      0.7479452055,
      "2023-10-22T07:03:03.000"
    ],
    [
      "serverless-offline",
      1.0410958904,
      "2024-04-13T02:28:05.000"
    ],
    [
      "serverless-offline-ssm",
      0.0,
      "2025-04-09T00:28:53.000"
    ],
    [
      "serverless-online",
      0.0,
      "2024-04-13T02:28:05.000"
    ],
    [
      "serverless-plugin-scripts",
      0.0,
      "2025-04-09T00:28:53.000"
    ],
    [
      "serverless-plugin-warmup",
      0.0,
      "2024-04-13T02:28:05.000"
    ],
    [
      "serverless-s3-bucket-helper",
      -1.0,
      "2025-04-09T00:28:53.000"
    ],
    [
      "serverless-stack-termination-protection",
      1.9643835616,
      "2025-04-09T00:28:53.000"
    ],
    [
      "@stratiformdigital/serverless-stage-destroyer",
      0.0,
      "2025-04-09T00:28:53.000"
    ],
    [
      "typescript",
      0.5616438356,
      "2023-10-22T07:03:03.000"
    ],
    [
      "typescript",
      1.095890411,
      "2024-03-11T01:24:26.000"
    ],
    [
      "typescript",
      1.1917808219,
      "2024-04-13T02:28:05.000"
    ],
    [
      "typescript",
      2.1780821918,
      "2025-04-09T00:28:53.000"
    ],
    [
      "@typescript-eslint/eslint-plugin",
      1.4,
      "2023-08-29T18:14:22.000"
    ],
    [
      "@typescript-eslint/eslint-plugin",
      1.5342465753,
      "2023-10-22T07:03:03.000"
    ],
    [
      "@typescript-eslint/eslint-plugin",
      1.9178082192,
      "2024-03-11T01:24:26.000"
    ],
    [
      "@typescript-eslint/eslint-plugin",
      2.0136986301,
      "2024-04-13T02:28:05.000"
    ],
    [
      "@typescript-eslint/eslint-plugin",
      3.0109589041,
      "2025-04-09T00:28:53.000"
    ],
    [
      "@typescript-eslint/parser",
      1.4,
      "2023-08-29T18:14:22.000"
    ],
    [
      "@typescript-eslint/parser",
      1.5342465753,
      "2023-10-22T07:03:03.000"
    ],
    [
      "@typescript-eslint/parser",
      1.9178082192,
      "2024-03-11T01:24:26.000"
    ],
    [
      "@typescript-eslint/parser",
      2.0136986301,
      "2024-04-13T02:28:05.000"
    ],
    [
      "@typescript-eslint/parser",
      3.0109589041,
      "2025-04-09T00:28:53.000"
    ],
    [
      "@types/dotenv",
      0.0,
      "2025-04-09T00:28:53.000"
    ],
    [
      "@types/flat",
      0.0,
      "2025-04-09T00:28:53.000"
    ],
    [
      "@types/node",
      -0.002739726,
      "2024-03-11T01:24:26.000"
    ],
    [
      "@types/node",
      0.0,
      "2024-04-13T02:28:05.000"
    ],
    [
      "@types/node",
      0.002739726,
      "2025-04-09T00:28:53.000"
    ],
    [
      "@types/node",
      0.0082191781,
      "2023-08-29T18:14:22.000"
    ],
    [
      "@types/yargs",
      -0.002739726,
      "2024-04-13T02:28:05.000"
    ],
    [
      "@types/yargs",
      0.2246575342,
      "2023-08-29T18:14:22.000"
    ],
    [
      "@types/yargs",
      0.7095890411,
      "2025-04-09T00:28:53.000"
    ],
    [
      "xml2js",
      0.1671232877,
      "2025-04-09T00:28:53.000"
    ],
    [
      "yargs",
      2.3890410959,
      "2025-04-09T00:28:53.000"
    ]
  ]
}
