{
  "url": "https://github.com/measureauthoringtool/madie-cql-library",
  "owner": "measureauthoringtool",
  "name": "madie-cql-library",
  "description": "This is a single-spa Application for the MADIE application's Stand alone CQL library logic.",
  "commits_count": 445,
  "issues_count": 0,
  "open_issues_count": 0,
  "closed_issues_count": 0,
  "pull_requests_count": 171,
  "open_pull_requests_count": 16,
  "merged_pull_requests_count": 131,
  "closed_pull_requests_count": 24,
  "forks_count": 2,
  "stargazers_count": 0,
  "watchers_count": 4,
  "created_at": "2022-03-04T14:34:49Z",
  "total_project_lines": 7920,
  "average_project_lines": 126,
  "total_project_comment_lines": 89,
  "average_project_comment_lines": 1,
  "total_project_blank_lines": 585,
  "average_blank_lines": 9,
  "predominant_langs": {
    "TypeScript": 209045,
    "JavaScript": 5790,
    "SCSS": 3752,
    "Shell": 116
  },
  "commits_by_month": {
    "2024/12": 7,
    "2024/11": 13,
    "2024/10": 9,
    "2024/9": 1
  },
  "average_issue_resolution_time": [],
  "new_commit_contributors_by_day_over_last_month": [],
  "new_commit_contributors_by_day_over_last_six_months": [
    [
      "2024-07-01T00:00:00.000Z",
      2
    ],
    [
      "2024-07-30T00:00:00.000Z",
      1
    ],
    [
      "2024-08-07T00:00:00.000Z",
      1
    ],
    [
      "2024-08-08T00:00:00.000Z",
      1
    ],
    [
      "2024-08-13T00:00:00.000Z",
      2
    ],
    [
      "2024-08-19T00:00:00.000Z",
      2
    ]
  ],
  "new_issues_by_day_over_last_month": [],
  "new_issues_by_day_over_last_six_months": [],
  "nadia_shields_badge_url": "https://img.shields.io/static/v1?label=project+type&message=midsize&color=ff0000",
  "nadia_color": "ff0000",
  "nadia_badge_name": "midsize",
  "repo_dependency_libyear_list": [
    [
      "@babel/core",
      0,
      "2024-11-01T01:11:26.000"
    ],
    [
      "@babel/eslint-parser",
      0,
      "2024-11-01T01:11:26.000"
    ],
    [
      "@babel/plugin-transform-react-jsx",
      0,
      "2024-11-01T01:11:26.000"
    ],
    [
      "@babel/plugin-transform-runtime",
      0,
      "2024-11-01T01:11:26.000"
    ],
    [
      "@babel/preset-env",
      0,
      "2024-11-01T01:11:26.000"
    ],
    [
      "@babel/preset-react",
      0,
      "2024-11-01T01:11:26.000"
    ],
    [
      "@babel/preset-typescript",
      0,
      "2024-11-01T01:11:26.000"
    ],
    [
      "@babel/runtime",
      0,
      "2024-11-01T01:11:26.000"
    ],
    [
      "@madie/madie-design-system",
      0.602739726,
      "2024-11-01T01:11:26.000"
    ],
    [
      "@madie/madie-models",
      0,
      "2024-11-01T01:11:26.000"
    ],
    [
      "@material-ui/core",
      0,
      "2024-11-01T01:11:26.000"
    ],
    [
      "@mui/icons-material",
      2.3808219178,
      "2024-11-01T01:11:26.000"
    ],
    [
      "@mui/material",
      0.2246575342,
      "2024-11-01T01:11:26.000"
    ],
    [
      "@testing-library/jest-dom",
      1.2904109589,
      "2024-11-01T01:11:26.000"
    ],
    [
      "@testing-library/react",
      2.3835616438,
      "2024-11-01T01:11:26.000"
    ],
    [
      "@testing-library/user-event",
      2.1945205479,
      "2024-11-01T01:11:26.000"
    ],
    [
      "@types/jest",
      2.3945205479,
      "2024-11-01T01:11:26.000"
    ],
    [
      "@types/react",
      0.0684931507,
      "2024-11-01T01:11:26.000"
    ],
    [
      "@types/react-dom",
      3.2630136986,
      "2024-11-01T01:11:26.000"
    ],
    [
      "@types/styled-components",
      0,
      "2024-11-01T01:11:26.000"
    ],
    [
      "@types/systemjs",
      0,
      "2024-11-01T01:11:26.000"
    ],
    [
      "@types/testing-library__jest-dom",
      0.0575342466,
      "2024-11-01T01:11:26.000"
    ],
    [
      "@types/webpack-env",
      0,
      "2024-11-01T01:11:26.000"
    ],
    [
      "allotment",
      0,
      "2024-11-01T01:11:26.000"
    ],
    [
      "autoprefixer",
      0,
      "2024-11-01T01:11:26.000"
    ],
    [
      "axios",
      0,
      "2024-11-01T01:11:26.000"
    ],
    [
      "babel-jest",
      1.5890410959,
      "2024-11-01T01:11:26.000"
    ],
    [
      "babel-plugin-dynamic-import-node",
      0,
      "2024-11-01T01:11:26.000"
    ],
    [
      "classnames",
      0,
      "2024-11-01T01:11:26.000"
    ],
    [
      "concurrently",
      2.7315068493,
      "2024-11-01T01:11:26.000"
    ],
    [
      "cross-env",
      0,
      "2024-11-01T01:11:26.000"
    ],
    [
      "eslint",
      3.2191780822,
      "2024-11-01T01:11:26.000"
    ],
    [
      "eslint-config-prettier",
      0.3479452055,
      "2024-11-01T01:11:26.000"
    ],
    [
      "eslint-config-ts-react-important-stuff",
      0,
      "2024-11-01T01:11:26.000"
    ],
    [
      "eslint-plugin-prettier",
      2.0493150685,
      "2024-11-01T01:11:26.000"
    ],
    [
      "formik",
      0,
      "2024-11-01T01:11:26.000"
    ],
    [
      "husky",
      2.8931506849,
      "2024-11-01T01:11:26.000"
    ],
    [
      "identity-obj-proxy",
      0,
      "2024-11-01T01:11:26.000"
    ],
    [
      "jest",
      1.5890410959,
      "2024-11-01T01:11:26.000"
    ],
    [
      "jest-cli",
      1.5890410959,
      "2024-11-01T01:11:26.000"
    ],
    [
      "postcss",
      0,
      "2024-11-01T01:11:26.000"
    ],
    [
      "postcss-loader",
      2.2547945205,
      "2024-11-01T01:11:26.000"
    ],
    [
      "postcss-preset-env",
      0.295890411,
      "2024-11-01T01:11:26.000"
    ],
    [
      "prettier",
      1.2246575342,
      "2024-11-01T01:11:26.000"
    ],
    [
      "pretty-quick",
      0,
      "2024-11-01T01:11:26.000"
    ],
    [
      "query-string",
      1.8520547945,
      "2024-11-01T01:11:26.000"
    ],
    [
      "react",
      3.095890411,
      "2024-11-01T01:11:26.000"
    ],
    [
      "react-dom",
      3.095890411,
      "2024-11-01T01:11:26.000"
    ],
    [
      "react-is",
      0,
      "2024-11-01T01:11:26.000"
    ],
    [
      "react-router",
      2.0273972603,
      "2024-11-01T01:11:26.000"
    ],
    [
      "react-router-dom",
      2.0273972603,
      "2024-11-01T01:11:26.000"
    ],
    [
      "sass",
      0,
      "2024-11-01T01:11:26.000"
    ],
    [
      "sass-loader",
      2.7095890411,
      "2024-11-01T01:11:26.000"
    ],
    [
      "single-spa",
      1.2904109589,
      "2024-11-01T01:11:26.000"
    ],
    [
      "single-spa-react",
      2.6684931507,
      "2024-11-01T01:11:26.000"
    ],
    [
      "styled-components",
      1.4657534247,
      "2024-11-01T01:11:26.000"
    ],
    [
      "tailwindcss",
      0,
      "2024-11-01T01:11:26.000"
    ],
    [
      "ts-config-single-spa",
      0,
      "2024-11-01T01:11:26.000"
    ],
    [
      "twin.macro",
      0,
      "2024-11-01T01:11:26.000"
    ],
    [
      "typescript",
      1.6904109589,
      "2024-11-01T01:11:26.000"
    ],
    [
      "webpack",
      0,
      "2024-11-01T01:11:26.000"
    ],
    [
      "webpack-cli",
      1.3671232877,
      "2024-11-01T01:11:26.000"
    ],
    [
      "webpack-config-single-spa-react",
      0.7424657534,
      "2024-11-01T01:11:26.000"
    ],
    [
      "webpack-config-single-spa-react-ts",
      0.7424657534,
      "2024-11-01T01:11:26.000"
    ],
    [
      "webpack-config-single-spa-ts",
      0.7424657534,
      "2024-11-01T01:11:26.000"
    ],
    [
      "webpack-dev-server",
      0,
      "2024-11-01T01:11:26.000"
    ],
    [
      "webpack-merge",
      1.1150684932,
      "2024-11-01T01:11:26.000"
    ],
    [
      "yup",
      2.397260274,
      "2024-11-01T01:11:26.000"
    ]
  ],
  "cocomo": {
    "languageSummary": [
      {
        "Name": "TypeScript",
        "Bytes": 209045,
        "CodeBytes": 0,
        "Lines": 6803,
        "Code": 6277,
        "Comment": 53,
        "Blank": 473,
        "Complexity": 213,
        "Count": 38,
        "WeightedComplexity": 0,
        "Files": [],
        "LineLength": null,
        "ULOC": 0
      },
      {
        "Name": "JSON",
        "Bytes": 4833,
        "CodeBytes": 0,
        "Lines": 173,
        "Code": 173,
        "Comment": 0,
        "Blank": 0,
        "Complexity": 0,
        "Count": 5,
        "WeightedComplexity": 0,
        "Files": [],
        "LineLength": null,
        "ULOC": 0
      },
      {
        "Name": "JavaScript",
        "Bytes": 5790,
        "CodeBytes": 0,
        "Lines": 250,
        "Code": 239,
        "Comment": 4,
        "Blank": 7,
        "Complexity": 2,
        "Count": 5,
        "WeightedComplexity": 0,
        "Files": [],
        "LineLength": null,
        "ULOC": 0
      },
      {
        "Name": "TypeScript Typings",
        "Bytes": 9081,
        "CodeBytes": 0,
        "Lines": 360,
        "Code": 292,
        "Comment": 23,
        "Blank": 45,
        "Complexity": 2,
        "Count": 5,
        "WeightedComplexity": 0,
        "Files": [],
        "LineLength": null,
        "ULOC": 0
      },
      {
        "Name": "YAML",
        "Bytes": 5620,
        "CodeBytes": 0,
        "Lines": 187,
        "Code": 148,
        "Comment": 8,
        "Blank": 31,
        "Complexity": 0,
        "Count": 3,
        "WeightedComplexity": 0,
        "Files": [],
        "LineLength": null,
        "ULOC": 0
      },
      {
        "Name": "Markdown",
        "Bytes": 1425,
        "CodeBytes": 0,
        "Lines": 30,
        "Code": 22,
        "Comment": 0,
        "Blank": 8,
        "Complexity": 0,
        "Count": 2,
        "WeightedComplexity": 0,
        "Files": [],
        "LineLength": null,
        "ULOC": 0
      },
      {
        "Name": "Sass",
        "Bytes": 3752,
        "CodeBytes": 0,
        "Lines": 197,
        "Code": 173,
        "Comment": 0,
        "Blank": 24,
        "Complexity": 0,
        "Count": 2,
        "WeightedComplexity": 0,
        "Files": [],
        "LineLength": null,
        "ULOC": 0
      },
      {
        "Name": "License",
        "Bytes": 7048,
        "CodeBytes": 0,
        "Lines": 121,
        "Code": 109,
        "Comment": 0,
        "Blank": 12,
        "Complexity": 0,
        "Count": 1,
        "WeightedComplexity": 0,
        "Files": [],
        "LineLength": null,
        "ULOC": 0
      },
      {
        "Name": "Shell",
        "Bytes": 116,
        "CodeBytes": 0,
        "Lines": 4,
        "Code": 2,
        "Comment": 1,
        "Blank": 1,
        "Complexity": 1,
        "Count": 1,
        "WeightedComplexity": 0,
        "Files": [],
        "LineLength": null,
        "ULOC": 0
      },
      {
        "Name": "TOML",
        "Bytes": 80,
        "CodeBytes": 0,
        "Lines": 3,
        "Code": 3,
        "Comment": 0,
        "Blank": 0,
        "Complexity": 0,
        "Count": 1,
        "WeightedComplexity": 0,
        "Files": [],
        "LineLength": null,
        "ULOC": 0
      }
    ],
    "estimatedCost_low": 202577.27105751698,
    "estimatedScheduleMonths_low": 7.764818236473174,
    "estimatedPeople_low": 2.541610116565296,
    "estimatedCost_high": 631319.2531974851,
    "estimatedScheduleMonths_high": 7.764818236473174,
    "estimatedPeople_high": 2.541610116565296,
    "dryness_table": "───────────────────────────────────────────────────────────────────────────────\nLanguage                 Files     Lines   Blanks  Comments     Code Complexity\n───────────────────────────────────────────────────────────────────────────────\nTypeScript                  38      6803      473        53     6277        213\n(ULOC)                              3010\n-------------------------------------------------------------------------------\nJSON                         5       173        0         0      173          0\n(ULOC)                               150\n-------------------------------------------------------------------------------\nJavaScript                   5       250        7         4      239          2\n(ULOC)                               204\n-------------------------------------------------------------------------------\nTypeScript Typings           5       360       45        23      292          2\n(ULOC)                               238\n-------------------------------------------------------------------------------\nYAML                         3       187       31         8      148          0\n(ULOC)                               107\n-------------------------------------------------------------------------------\nMarkdown                     2        30        8         0       22          0\n(ULOC)                                23\n-------------------------------------------------------------------------------\nSass                         2       197       24         0      173          0\n(ULOC)                               127\n-------------------------------------------------------------------------------\nLicense                      1       121       12         0      109          0\n(ULOC)                               110\n-------------------------------------------------------------------------------\nShell                        1         4        1         1        2          1\n(ULOC)                                 4\n-------------------------------------------------------------------------------\nTOML                         1         3        0         0        3          0\n(ULOC)                                 3\n───────────────────────────────────────────────────────────────────────────────\nTotal                       63      8128      601        89     7438        218\n───────────────────────────────────────────────────────────────────────────────\nUnique Lines of Code (ULOC)         3931\nDRYness %                           0.48\n───────────────────────────────────────────────────────────────────────────────\nEstimated Cost to Develop (organic) $222,138\nEstimated Schedule Effort (organic) 7.76 months\nEstimated People Required (organic) 2.54\n───────────────────────────────────────────────────────────────────────────────\nProcessed 246790 bytes, 0.247 megabytes (SI)\n───────────────────────────────────────────────────────────────────────────────\n"
  },
  "ossf_scorecard": {
    "date": "2024-12-15T10:57:25Z",
    "repo": {
      "name": "github.com/measureauthoringtool/madie-cql-library",
      "commit": "a2b3d0e1506148fd9f15455a6de76da1be506d4e"
    },
    "scorecard": {
      "version": "v5.0.0-113-g009b2a34",
      "commit": "009b2a345fc2d639f9ba8c700cceb553c1b3ad55"
    },
    "score": 5.6,
    "checks": [
      {
        "details": null,
        "score": 10,
        "reason": "no binaries found in the repo",
        "name": "Binary-Artifacts",
        "documentation": {
          "url": "https://github.com/ossf/scorecard/blob/009b2a345fc2d639f9ba8c700cceb553c1b3ad55/docs/checks.md#binary-artifacts",
          "short": "Determines if the project has generated executable (binary) artifacts in the source repository."
        }
      },
      {
        "details": null,
        "score": 6,
        "reason": "branch protection is not maximal on development and all release branches",
        "name": "Branch-Protection",
        "documentation": {
          "url": "https://github.com/ossf/scorecard/blob/009b2a345fc2d639f9ba8c700cceb553c1b3ad55/docs/checks.md#branch-protection",
          "short": "Determines if the default and release branches are protected with GitHub's branch protection settings."
        }
      },
      {
        "details": null,
        "score": 10,
        "reason": "9 out of 9 merged PRs checked by a CI test -- score normalized to 10",
        "name": "CI-Tests",
        "documentation": {
          "url": "https://github.com/ossf/scorecard/blob/009b2a345fc2d639f9ba8c700cceb553c1b3ad55/docs/checks.md#ci-tests",
          "short": "Determines if the project runs tests before pull requests are merged."
        }
      },
      {
        "details": null,
        "score": 0,
        "reason": "no effort to earn an OpenSSF best practices badge detected",
        "name": "CII-Best-Practices",
        "documentation": {
          "url": "https://github.com/ossf/scorecard/blob/009b2a345fc2d639f9ba8c700cceb553c1b3ad55/docs/checks.md#cii-best-practices",
          "short": "Determines if the project has an OpenSSF (formerly CII) Best Practices Badge."
        }
      },
      {
        "details": null,
        "score": 10,
        "reason": "all changesets reviewed",
        "name": "Code-Review",
        "documentation": {
          "url": "https://github.com/ossf/scorecard/blob/009b2a345fc2d639f9ba8c700cceb553c1b3ad55/docs/checks.md#code-review",
          "short": "Determines if the project requires human code review before pull requests (aka merge requests) are merged."
        }
      },
      {
        "details": null,
        "score": 6,
        "reason": "project has 2 contributing companies or organizations -- score normalized to 6",
        "name": "Contributors",
        "documentation": {
          "url": "https://github.com/ossf/scorecard/blob/009b2a345fc2d639f9ba8c700cceb553c1b3ad55/docs/checks.md#contributors",
          "short": "Determines if the project has a set of contributors from multiple organizations (e.g., companies)."
        }
      },
      {
        "details": null,
        "score": 10,
        "reason": "no dangerous workflow patterns detected",
        "name": "Dangerous-Workflow",
        "documentation": {
          "url": "https://github.com/ossf/scorecard/blob/009b2a345fc2d639f9ba8c700cceb553c1b3ad55/docs/checks.md#dangerous-workflow",
          "short": "Determines if the project's GitHub Action workflows avoid dangerous patterns."
        }
      },
      {
        "details": null,
        "score": 0,
        "reason": "no update tool detected",
        "name": "Dependency-Update-Tool",
        "documentation": {
          "url": "https://github.com/ossf/scorecard/blob/009b2a345fc2d639f9ba8c700cceb553c1b3ad55/docs/checks.md#dependency-update-tool",
          "short": "Determines if the project uses a dependency update tool."
        }
      },
      {
        "details": null,
        "score": 0,
        "reason": "project is not fuzzed",
        "name": "Fuzzing",
        "documentation": {
          "url": "https://github.com/ossf/scorecard/blob/009b2a345fc2d639f9ba8c700cceb553c1b3ad55/docs/checks.md#fuzzing",
          "short": "Determines if the project uses fuzzing."
        }
      },
      {
        "details": null,
        "score": 10,
        "reason": "license file detected",
        "name": "License",
        "documentation": {
          "url": "https://github.com/ossf/scorecard/blob/009b2a345fc2d639f9ba8c700cceb553c1b3ad55/docs/checks.md#license",
          "short": "Determines if the project has defined a license."
        }
      },
      {
        "details": null,
        "score": 10,
        "reason": "30 commit(s) and 0 issue activity found in the last 90 days -- score normalized to 10",
        "name": "Maintained",
        "documentation": {
          "url": "https://github.com/ossf/scorecard/blob/009b2a345fc2d639f9ba8c700cceb553c1b3ad55/docs/checks.md#maintained",
          "short": "Determines if the project is \"actively maintained\"."
        }
      },
      {
        "details": null,
        "score": -1,
        "reason": "packaging workflow not detected",
        "name": "Packaging",
        "documentation": {
          "url": "https://github.com/ossf/scorecard/blob/009b2a345fc2d639f9ba8c700cceb553c1b3ad55/docs/checks.md#packaging",
          "short": "Determines if the project is published as a package that others can easily download, install, easily update, and uninstall."
        }
      },
      {
        "details": null,
        "score": 2,
        "reason": "dependency not pinned by hash detected -- score normalized to 2",
        "name": "Pinned-Dependencies",
        "documentation": {
          "url": "https://github.com/ossf/scorecard/blob/009b2a345fc2d639f9ba8c700cceb553c1b3ad55/docs/checks.md#pinned-dependencies",
          "short": "Determines if the project has declared and pinned the dependencies of its build process."
        }
      },
      {
        "details": null,
        "score": 0,
        "reason": "SAST tool is not run on all commits -- score normalized to 0",
        "name": "SAST",
        "documentation": {
          "url": "https://github.com/ossf/scorecard/blob/009b2a345fc2d639f9ba8c700cceb553c1b3ad55/docs/checks.md#sast",
          "short": "Determines if the project uses static code analysis."
        }
      },
      {
        "details": null,
        "score": 0,
        "reason": "security policy file not detected",
        "name": "Security-Policy",
        "documentation": {
          "url": "https://github.com/ossf/scorecard/blob/009b2a345fc2d639f9ba8c700cceb553c1b3ad55/docs/checks.md#security-policy",
          "short": "Determines if the project has published a security policy."
        }
      },
      {
        "details": null,
        "score": -1,
        "reason": "no releases found",
        "name": "Signed-Releases",
        "documentation": {
          "url": "https://github.com/ossf/scorecard/blob/009b2a345fc2d639f9ba8c700cceb553c1b3ad55/docs/checks.md#signed-releases",
          "short": "Determines if the project cryptographically signs release artifacts."
        }
      },
      {
        "details": null,
        "score": 0,
        "reason": "detected GitHub workflow tokens with excessive permissions",
        "name": "Token-Permissions",
        "documentation": {
          "url": "https://github.com/ossf/scorecard/blob/009b2a345fc2d639f9ba8c700cceb553c1b3ad55/docs/checks.md#token-permissions",
          "short": "Determines if the project's workflows follow the principle of least privilege."
        }
      },
      {
        "details": null,
        "score": 10,
        "reason": "0 existing vulnerabilities detected",
        "name": "Vulnerabilities",
        "documentation": {
          "url": "https://github.com/ossf/scorecard/blob/009b2a345fc2d639f9ba8c700cceb553c1b3ad55/docs/checks.md#vulnerabilities",
          "short": "Determines if the project has open, known unfixed vulnerabilities."
        }
      }
    ],
    "metadata": null
  }
}
