{
    "url": "https://github.com/CMSgov/CMS-GoogleMaps-Socrata-Integration",
    "owner": "CMSgov",
    "name": "CMS-GoogleMaps-Socrata-Integration",
    "description": "Google Maps and Socrata Integration (originally developed for innovation.cms.gov)",
    "commits_count": 1,
    "issues_count": 0,
    "open_issues_count": 0,
    "closed_issues_count": 0,
    "pull_requests_count": 0,
    "open_pull_requests_count": 0,
    "merged_pull_requests_count": 0,
    "closed_pull_requests_count": 0,
    "forks_count": 8,
    "stargazers_count": 7,
    "watchers_count": 9,
    "total_project_lines": 3941,
    "average_project_lines": 493,
    "total_project_comment_lines": 283,
    "average_project_comment_lines": 35,
    "total_project_blank_lines": 609,
    "average_blank_lines": 76,
    "commits_by_month": {
        "2013/6": 1
    },
    "new_commit_contributors_by_day_over_last_month": [],
    "new_commit_contributors_by_day_over_last_six_months": [],
    "new_issues_by_day_over_last_month": [],
    "new_issues_by_day_over_last_six_months": [],
    "nadia_shields_badge_url": "https://img.shields.io/static/v1?label=project+type&message=toy&color=0000ff",
    "nadia_color": "0000ff",
    "nadia_badge_name": "toy"
}