{
  "url": "https://github.com/DSACMS/iv-cbv-payroll",
  "owner": "DSACMS",
  "name": "iv-cbv-payroll",
  "description": null,
  "commits_count": 640,
  "issues_count": 3,
  "open_issues_count": 2,
  "closed_issues_count": 1,
  "pull_requests_count": 472,
  "open_pull_requests_count": 5,
  "merged_pull_requests_count": 428,
  "closed_pull_requests_count": 39,
  "forks_count": 2,
  "stargazers_count": 6,
  "watchers_count": 4,
  "created_at": "2024-04-22T22:34:18Z",
  "predominant_langs": {
    "Ruby": 398356,
    "HCL": 179824,
    "Shell": 64833,
    "HTML": 55199,
    "JavaScript": 32633,
    "Makefile": 18688,
    "Python": 11822,
    "Dockerfile": 6431,
    "TypeScript": 5178,
    "Go": 4675,
    "SCSS": 4514,
    "CSS": 145
  },
  "commits_by_month": {
    "2025/2": 30
  },
  "cocomo": {
    "languageSummary": [
      {
        "Name": "Ruby",
        "Bytes": 387844,
        "CodeBytes": 0,
        "Lines": 11574,
        "Code": 8940,
        "Comment": 903,
        "Blank": 1731,
        "Complexity": 291,
        "Count": 222,
        "WeightedComplexity": 0,
        "Files": [],
        "LineLength": null,
        "ULOC": 0
      },
      {
        "Name": "Terraform",
        "Bytes": 179824,
        "CodeBytes": 0,
        "Lines": 5773,
        "Code": 3870,
        "Comment": 1160,
        "Blank": 743,
        "Complexity": 361,
        "Count": 133,
        "WeightedComplexity": 0,
        "Files": [],
        "LineLength": null,
        "ULOC": 0
      },
      {
        "Name": "Markdown",
        "Bytes": 147863,
        "CodeBytes": 0,
        "Lines": 2817,
        "Code": 1890,
        "Comment": 0,
        "Blank": 927,
        "Complexity": 0,
        "Count": 52,
        "WeightedComplexity": 0,
        "Files": [],
        "LineLength": null,
        "ULOC": 0
      },
      {
        "Name": "Ruby HTML",
        "Bytes": 55199,
        "CodeBytes": 0,
        "Lines": 1389,
        "Code": 1249,
        "Comment": 0,
        "Blank": 140,
        "Complexity": 106,
        "Count": 49,
        "WeightedComplexity": 0,
        "Files": [],
        "LineLength": null,
        "ULOC": 0
      },
      {
        "Name": "YAML",
        "Bytes": 141548,
        "CodeBytes": 0,
        "Lines": 3242,
        "Code": 2658,
        "Comment": 330,
        "Blank": 254,
        "Complexity": 0,
        "Count": 49,
        "WeightedComplexity": 0,
        "Files": [],
        "LineLength": null,
        "ULOC": 0
      },
      {
        "Name": "BASH",
        "Bytes": 59979,
        "CodeBytes": 0,
        "Lines": 1543,
        "Code": 887,
        "Comment": 450,
        "Blank": 206,
        "Complexity": 74,
        "Count": 32,
        "WeightedComplexity": 0,
        "Files": [],
        "LineLength": null,
        "ULOC": 0
      },
      {
        "Name": "JavaScript",
        "Bytes": 32633,
        "CodeBytes": 0,
        "Lines": 971,
        "Code": 764,
        "Comment": 63,
        "Blank": 144,
        "Complexity": 16,
        "Count": 26,
        "WeightedComplexity": 0,
        "Files": [],
        "LineLength": null,
        "ULOC": 0
      },
      {
        "Name": "JSON",
        "Bytes": 24981,
        "CodeBytes": 0,
        "Lines": 894,
        "Code": 893,
        "Comment": 0,
        "Blank": 1,
        "Complexity": 0,
        "Count": 19,
        "WeightedComplexity": 0,
        "Files": [],
        "LineLength": null,
        "ULOC": 0
      },
      {
        "Name": "Shell",
        "Bytes": 4854,
        "CodeBytes": 0,
        "Lines": 220,
        "Code": 152,
        "Comment": 22,
        "Blank": 46,
        "Complexity": 20,
        "Count": 10,
        "WeightedComplexity": 0,
        "Files": [],
        "LineLength": null,
        "ULOC": 0
      },
      {
        "Name": "TypeScript",
        "Bytes": 5178,
        "CodeBytes": 0,
        "Lines": 192,
        "Code": 164,
        "Comment": 1,
        "Blank": 27,
        "Complexity": 29,
        "Count": 5,
        "WeightedComplexity": 0,
        "Files": [],
        "LineLength": null,
        "ULOC": 0
      },
      {
        "Name": "Python",
        "Bytes": 11822,
        "CodeBytes": 0,
        "Lines": 346,
        "Code": 288,
        "Comment": 16,
        "Blank": 42,
        "Complexity": 12,
        "Count": 4,
        "WeightedComplexity": 0,
        "Files": [],
        "LineLength": null,
        "ULOC": 0
      },
      {
        "Name": "Plain Text",
        "Bytes": 110,
        "CodeBytes": 0,
        "Lines": 3,
        "Code": 3,
        "Comment": 0,
        "Blank": 0,
        "Complexity": 0,
        "Count": 3,
        "WeightedComplexity": 0,
        "Files": [],
        "LineLength": null,
        "ULOC": 0
      },
      {
        "Name": "Sass",
        "Bytes": 4514,
        "CodeBytes": 0,
        "Lines": 215,
        "Code": 159,
        "Comment": 32,
        "Blank": 24,
        "Complexity": 0,
        "Count": 3,
        "WeightedComplexity": 0,
        "Files": [],
        "LineLength": null,
        "ULOC": 0
      },
      {
        "Name": "TypeScript Typings",
        "Bytes": 903,
        "CodeBytes": 0,
        "Lines": 34,
        "Code": 30,
        "Comment": 0,
        "Blank": 4,
        "Complexity": 3,
        "Count": 3,
        "WeightedComplexity": 0,
        "Files": [],
        "LineLength": null,
        "ULOC": 0
      },
      {
        "Name": "Go",
        "Bytes": 4675,
        "CodeBytes": 0,
        "Lines": 129,
        "Code": 97,
        "Comment": 14,
        "Blank": 18,
        "Complexity": 3,
        "Count": 2,
        "WeightedComplexity": 0,
        "Files": [],
        "LineLength": null,
        "ULOC": 0
      },
      {
        "Name": "Makefile",
        "Bytes": 18688,
        "CodeBytes": 0,
        "Lines": 484,
        "Code": 309,
        "Comment": 72,
        "Blank": 103,
        "Complexity": 12,
        "Count": 2,
        "WeightedComplexity": 0,
        "Files": [],
        "LineLength": null,
        "ULOC": 0
      },
      {
        "Name": "Rakefile",
        "Bytes": 317,
        "CodeBytes": 0,
        "Lines": 10,
        "Code": 5,
        "Comment": 3,
        "Blank": 2,
        "Complexity": 0,
        "Count": 2,
        "WeightedComplexity": 0,
        "Files": [],
        "LineLength": null,
        "ULOC": 0
      },
      {
        "Name": "CSS",
        "Bytes": 145,
        "CodeBytes": 0,
        "Lines": 5,
        "Code": 4,
        "Comment": 1,
        "Blank": 0,
        "Complexity": 0,
        "Count": 1,
        "WeightedComplexity": 0,
        "Files": [],
        "LineLength": null,
        "ULOC": 0
      },
      {
        "Name": "CSV",
        "Bytes": 106700,
        "CodeBytes": 0,
        "Lines": 444,
        "Code": 444,
        "Comment": 0,
        "Blank": 0,
        "Complexity": 0,
        "Count": 1,
        "WeightedComplexity": 0,
        "Files": [],
        "LineLength": null,
        "ULOC": 0
      },
      {
        "Name": "Docker ignore",
        "Bytes": 15,
        "CodeBytes": 0,
        "Lines": 2,
        "Code": 1,
        "Comment": 0,
        "Blank": 1,
        "Complexity": 0,
        "Count": 1,
        "WeightedComplexity": 0,
        "Files": [],
        "LineLength": null,
        "ULOC": 0
      },
      {
        "Name": "Dockerfile",
        "Bytes": 6431,
        "CodeBytes": 0,
        "Lines": 177,
        "Code": 88,
        "Comment": 50,
        "Blank": 39,
        "Complexity": 22,
        "Count": 1,
        "WeightedComplexity": 0,
        "Files": [],
        "LineLength": null,
        "ULOC": 0
      },
      {
        "Name": "Gemfile",
        "Bytes": 3362,
        "CodeBytes": 0,
        "Lines": 125,
        "Code": 68,
        "Comment": 26,
        "Blank": 31,
        "Complexity": 0,
        "Count": 1,
        "WeightedComplexity": 0,
        "Files": [],
        "LineLength": null,
        "ULOC": 0
      },
      {
        "Name": "License",
        "Bytes": 7048,
        "CodeBytes": 0,
        "Lines": 121,
        "Code": 109,
        "Comment": 0,
        "Blank": 12,
        "Complexity": 0,
        "Count": 1,
        "WeightedComplexity": 0,
        "Files": [],
        "LineLength": null,
        "ULOC": 0
      },
      {
        "Name": "SQL",
        "Bytes": 28,
        "CodeBytes": 0,
        "Lines": 1,
        "Code": 1,
        "Comment": 0,
        "Blank": 0,
        "Complexity": 0,
        "Count": 1,
        "WeightedComplexity": 0,
        "Files": [],
        "LineLength": null,
        "ULOC": 0
      }
    ],
    "estimatedCost_low": 664999.0165833622,
    "estimatedScheduleMonths_low": 12.198285755998546,
    "estimatedPeople_low": 5.310943829730841,
    "estimatedCost_high": 2072427.377142772,
    "estimatedScheduleMonths_high": 12.198285755998546,
    "estimatedPeople_high": 5.310943829730841,
    "dryness_table": "───────────────────────────────────────────────────────────────────────────────\nLanguage                 Files     Lines   Blanks  Comments     Code Complexity\n───────────────────────────────────────────────────────────────────────────────\nRuby                       222     11574     1731       903     8940        291\n(ULOC)                              6185\n-------------------------------------------------------------------------------\nTerraform                  133      5773      743      1160     3870        361\n(ULOC)                              2871\n-------------------------------------------------------------------------------\nMarkdown                    52      2817      927         0     1890          0\n(ULOC)                              1547\n-------------------------------------------------------------------------------\nRuby HTML                   49      1389      140         0     1249        106\n(ULOC)                               802\n-------------------------------------------------------------------------------\nYAML                        49      3242      254       330     2658          0\n(ULOC)                              2090\n-------------------------------------------------------------------------------\nBASH                        32      1543      206       450      887         74\n(ULOC)                               919\n-------------------------------------------------------------------------------\nJavaScript                  26       971      144        63      764         16\n(ULOC)                               581\n-------------------------------------------------------------------------------\nJSON                        19       894        1         0      893          0\n(ULOC)                               326\n-------------------------------------------------------------------------------\nShell                       10       220       46        22      152         20\n(ULOC)                               141\n-------------------------------------------------------------------------------\nTypeScript                   5       192       27         1      164         29\n(ULOC)                               130\n-------------------------------------------------------------------------------\nPython                       4       346       42        16      288         12\n(ULOC)                               225\n-------------------------------------------------------------------------------\nPlain Text                   3         3        0         0        3          0\n(ULOC)                                 3\n-------------------------------------------------------------------------------\nSass                         3       215       24        32      159          0\n(ULOC)                               134\n-------------------------------------------------------------------------------\nTypeScript Typings           3        34        4         0       30          3\n(ULOC)                                28\n-------------------------------------------------------------------------------\nGo                           2       129       18        14       97          3\n(ULOC)                                83\n-------------------------------------------------------------------------------\nMakefile                     2       484      103        72      309         12\n(ULOC)                               312\n-------------------------------------------------------------------------------\nRakefile                     2        10        2         3        5          0\n(ULOC)                                 9\n-------------------------------------------------------------------------------\nCSS                          1         5        0         1        4          0\n(ULOC)                                 5\n-------------------------------------------------------------------------------\nCSV                          1       444        0         0      444          0\n(ULOC)                               376\n-------------------------------------------------------------------------------\nDocker ignore                1         2        1         0        1          0\n(ULOC)                                 1\n-------------------------------------------------------------------------------\nDockerfile                   1       177       39        50       88         22\n(ULOC)                               118\n-------------------------------------------------------------------------------\nGemfile                      1       125       31        26       68          0\n(ULOC)                                92\n-------------------------------------------------------------------------------\nLicense                      1       121       12         0      109          0\n(ULOC)                               110\n-------------------------------------------------------------------------------\nSQL                          1         1        0         0        1          0\n(ULOC)                                 1\n───────────────────────────────────────────────────────────────────────────────\nTotal                      623     30711     4495      3143    23073        949\n───────────────────────────────────────────────────────────────────────────────\nUnique Lines of Code (ULOC)        16909\nDRYness %                           0.55\n───────────────────────────────────────────────────────────────────────────────\nEstimated Cost to Develop (organic) $729,213\nEstimated Schedule Effort (organic) 12.20 months\nEstimated People Required (organic) 5.31\n───────────────────────────────────────────────────────────────────────────────\nProcessed 1204661 bytes, 1.205 megabytes (SI)\n───────────────────────────────────────────────────────────────────────────────\n"
  },
  "ossf_scorecard": {
    "date": "2025-02-23T16:11:44Z",
    "repo": {
      "name": "github.com/DSACMS/iv-cbv-payroll",
      "commit": "ab90d33ae75d843899ae2cf73be4742df73afb85"
    },
    "scorecard": {
      "version": "v5.1.1-5-g3b42b6e7",
      "commit": "3b42b6e7d8c66543d10c7f5ac5d3ecc0d1e56e5a"
    },
    "score": 4.9,
    "checks": [
      {
        "details": null,
        "score": 10,
        "reason": "no binaries found in the repo",
        "name": "Binary-Artifacts",
        "documentation": {
          "url": "https://github.com/ossf/scorecard/blob/3b42b6e7d8c66543d10c7f5ac5d3ecc0d1e56e5a/docs/checks.md#binary-artifacts",
          "short": "Determines if the project has generated executable (binary) artifacts in the source repository."
        }
      },
      {
        "details": null,
        "score": 3,
        "reason": "branch protection is not maximal on development and all release branches",
        "name": "Branch-Protection",
        "documentation": {
          "url": "https://github.com/ossf/scorecard/blob/3b42b6e7d8c66543d10c7f5ac5d3ecc0d1e56e5a/docs/checks.md#branch-protection",
          "short": "Determines if the default and release branches are protected with GitHub's branch protection settings."
        }
      },
      {
        "details": null,
        "score": 10,
        "reason": "25 out of 25 merged PRs checked by a CI test -- score normalized to 10",
        "name": "CI-Tests",
        "documentation": {
          "url": "https://github.com/ossf/scorecard/blob/3b42b6e7d8c66543d10c7f5ac5d3ecc0d1e56e5a/docs/checks.md#ci-tests",
          "short": "Determines if the project runs tests before pull requests are merged."
        }
      },
      {
        "details": null,
        "score": 0,
        "reason": "no effort to earn an OpenSSF best practices badge detected",
        "name": "CII-Best-Practices",
        "documentation": {
          "url": "https://github.com/ossf/scorecard/blob/3b42b6e7d8c66543d10c7f5ac5d3ecc0d1e56e5a/docs/checks.md#cii-best-practices",
          "short": "Determines if the project has an OpenSSF (formerly CII) Best Practices Badge."
        }
      },
      {
        "details": null,
        "score": 8,
        "reason": "Found 22/25 approved changesets -- score normalized to 8",
        "name": "Code-Review",
        "documentation": {
          "url": "https://github.com/ossf/scorecard/blob/3b42b6e7d8c66543d10c7f5ac5d3ecc0d1e56e5a/docs/checks.md#code-review",
          "short": "Determines if the project requires human code review before pull requests (aka merge requests) are merged."
        }
      },
      {
        "details": null,
        "score": 10,
        "reason": "project has 14 contributing companies or organizations",
        "name": "Contributors",
        "documentation": {
          "url": "https://github.com/ossf/scorecard/blob/3b42b6e7d8c66543d10c7f5ac5d3ecc0d1e56e5a/docs/checks.md#contributors",
          "short": "Determines if the project has a set of contributors from multiple organizations (e.g., companies)."
        }
      },
      {
        "details": null,
        "score": 10,
        "reason": "no dangerous workflow patterns detected",
        "name": "Dangerous-Workflow",
        "documentation": {
          "url": "https://github.com/ossf/scorecard/blob/3b42b6e7d8c66543d10c7f5ac5d3ecc0d1e56e5a/docs/checks.md#dangerous-workflow",
          "short": "Determines if the project's GitHub Action workflows avoid dangerous patterns."
        }
      },
      {
        "details": null,
        "score": 0,
        "reason": "no update tool detected",
        "name": "Dependency-Update-Tool",
        "documentation": {
          "url": "https://github.com/ossf/scorecard/blob/3b42b6e7d8c66543d10c7f5ac5d3ecc0d1e56e5a/docs/checks.md#dependency-update-tool",
          "short": "Determines if the project uses a dependency update tool."
        }
      },
      {
        "details": null,
        "score": 0,
        "reason": "project is not fuzzed",
        "name": "Fuzzing",
        "documentation": {
          "url": "https://github.com/ossf/scorecard/blob/3b42b6e7d8c66543d10c7f5ac5d3ecc0d1e56e5a/docs/checks.md#fuzzing",
          "short": "Determines if the project uses fuzzing."
        }
      },
      {
        "details": null,
        "score": 10,
        "reason": "license file detected",
        "name": "License",
        "documentation": {
          "url": "https://github.com/ossf/scorecard/blob/3b42b6e7d8c66543d10c7f5ac5d3ecc0d1e56e5a/docs/checks.md#license",
          "short": "Determines if the project has defined a license."
        }
      },
      {
        "details": null,
        "score": 10,
        "reason": "30 commit(s) and 0 issue activity found in the last 90 days -- score normalized to 10",
        "name": "Maintained",
        "documentation": {
          "url": "https://github.com/ossf/scorecard/blob/3b42b6e7d8c66543d10c7f5ac5d3ecc0d1e56e5a/docs/checks.md#maintained",
          "short": "Determines if the project is \"actively maintained\"."
        }
      },
      {
        "details": null,
        "score": -1,
        "reason": "packaging workflow not detected",
        "name": "Packaging",
        "documentation": {
          "url": "https://github.com/ossf/scorecard/blob/3b42b6e7d8c66543d10c7f5ac5d3ecc0d1e56e5a/docs/checks.md#packaging",
          "short": "Determines if the project is published as a package that others can easily download, install, easily update, and uninstall."
        }
      },
      {
        "details": null,
        "score": 0,
        "reason": "dependency not pinned by hash detected -- score normalized to 0",
        "name": "Pinned-Dependencies",
        "documentation": {
          "url": "https://github.com/ossf/scorecard/blob/3b42b6e7d8c66543d10c7f5ac5d3ecc0d1e56e5a/docs/checks.md#pinned-dependencies",
          "short": "Determines if the project has declared and pinned the dependencies of its build process."
        }
      },
      {
        "details": null,
        "score": 0,
        "reason": "SAST tool is not run on all commits -- score normalized to 0",
        "name": "SAST",
        "documentation": {
          "url": "https://github.com/ossf/scorecard/blob/3b42b6e7d8c66543d10c7f5ac5d3ecc0d1e56e5a/docs/checks.md#sast",
          "short": "Determines if the project uses static code analysis."
        }
      },
      {
        "details": null,
        "score": 10,
        "reason": "security policy file detected",
        "name": "Security-Policy",
        "documentation": {
          "url": "https://github.com/ossf/scorecard/blob/3b42b6e7d8c66543d10c7f5ac5d3ecc0d1e56e5a/docs/checks.md#security-policy",
          "short": "Determines if the project has published a security policy."
        }
      },
      {
        "details": null,
        "score": -1,
        "reason": "no releases found",
        "name": "Signed-Releases",
        "documentation": {
          "url": "https://github.com/ossf/scorecard/blob/3b42b6e7d8c66543d10c7f5ac5d3ecc0d1e56e5a/docs/checks.md#signed-releases",
          "short": "Determines if the project cryptographically signs release artifacts."
        }
      },
      {
        "details": null,
        "score": 0,
        "reason": "detected GitHub workflow tokens with excessive permissions",
        "name": "Token-Permissions",
        "documentation": {
          "url": "https://github.com/ossf/scorecard/blob/3b42b6e7d8c66543d10c7f5ac5d3ecc0d1e56e5a/docs/checks.md#token-permissions",
          "short": "Determines if the project's workflows follow the principle of least privilege."
        }
      },
      {
        "details": null,
        "score": 0,
        "reason": "11 existing vulnerabilities detected",
        "name": "Vulnerabilities",
        "documentation": {
          "url": "https://github.com/ossf/scorecard/blob/3b42b6e7d8c66543d10c7f5ac5d3ecc0d1e56e5a/docs/checks.md#vulnerabilities",
          "short": "Determines if the project has open, known unfixed vulnerabilities."
        }
      }
    ],
    "metadata": null
  },
  "total_project_lines": 28981,
  "average_project_lines": 51,
  "total_project_comment_lines": 3098,
  "average_project_comment_lines": 5,
  "total_project_blank_lines": 4271,
  "average_blank_lines": 7,
  "average_issue_resolution_time": [
    [
      "iv-cbv-payroll",
      "40 days 05:34:32"
    ]
  ],
  "new_commit_contributors_by_day_over_last_month": [
    [
      "2025-02-03T06:00:00.000Z",
      2
    ],
    [
      "2025-02-04T06:00:00.000Z",
      2
    ]
  ],
  "new_commit_contributors_by_day_over_last_six_months": [
    [
      "2024-09-16T05:00:00.000Z",
      1
    ],
    [
      "2024-09-18T05:00:00.000Z",
      1
    ],
    [
      "2024-09-19T05:00:00.000Z",
      1
    ],
    [
      "2024-09-30T05:00:00.000Z",
      1
    ],
    [
      "2024-11-01T05:00:00.000Z",
      1
    ],
    [
      "2024-11-12T06:00:00.000Z",
      1
    ],
    [
      "2024-11-19T06:00:00.000Z",
      1
    ],
    [
      "2025-01-03T06:00:00.000Z",
      1
    ],
    [
      "2025-02-03T06:00:00.000Z",
      1
    ]
  ],
  "new_issues_by_day_over_last_month": [],
  "new_issues_by_day_over_last_six_months": [
    [
      "2024-12-11T06:00:00.000Z",
      1
    ]
  ],
  "nadia_shields_badge_url": "https://img.shields.io/static/v1?label=project+type&message=midsize&color=ff0000",
  "nadia_color": "ff0000",
  "nadia_badge_name": "midsize",
  "repo_dependency_libyear_list": [
    [
      "@axe-core/playwright",
      -0.2164383562,
      "2025-02-06T07:30:00.000"
    ],
    [
      "@playwright/test",
      -0.0164383562,
      "2025-02-06T07:30:00.000"
    ],
    [
      "@types/node",
      -0.002739726,
      "2025-02-06T07:30:00.000"
    ],
    [
      "dotenv",
      0.0,
      "2025-02-06T07:30:00.000"
    ],
    [
      "pg8000",
      0.0,
      "2025-02-06T07:30:00.000"
    ]
  ]
}
