{
    "url": "https://github.com/DSACMS/metrics",
    "owner": "DSACMS",
    "name": "metrics",
    "description": "Experimentations in Open Source Repository Metrics",
    "commits_count": 439,
    "issues_count": 14,
    "open_issues_count": 10,
    "closed_issues_count": 4,
    "pull_requests_count": 83,
    "open_pull_requests_count": 1,
    "merged_pull_requests_count": 75,
    "closed_pull_requests_count": 7,
    "forks_count": 2,
    "stargazers_count": 3,
    "watchers_count": 3,
    "commits_by_month": {
        "2024/3": 17,
        "2024/2": 13
    },
    "new_commit_contributors_by_day_over_last_month": [
        [
            "2024-02-25T00:00:00.000Z",
            1
        ],
        [
            "2024-02-27T00:00:00.000Z",
            1
        ],
        [
            "2024-02-28T00:00:00.000Z",
            1
        ]
    ],
    "new_commit_contributors_by_day_over_last_six_months": [
        [
            "2023-10-10T00:00:00.000Z",
            1
        ],
        [
            "2023-10-12T00:00:00.000Z",
            1
        ],
        [
            "2023-10-17T00:00:00.000Z",
            1
        ],
        [
            "2023-10-31T00:00:00.000Z",
            1
        ],
        [
            "2023-11-01T00:00:00.000Z",
            1
        ],
        [
            "2023-11-21T00:00:00.000Z",
            3
        ]
    ],
    "new_issues_by_day_over_last_month": [],
    "new_issues_by_day_over_last_six_months": [
        [
            "2023-10-31T00:00:00.000Z",
            1
        ],
        [
            "2023-11-13T00:00:00.000Z",
            1
        ],
        [
            "2023-11-21T00:00:00.000Z",
            1
        ],
        [
            "2023-11-27T00:00:00.000Z",
            1
        ],
        [
            "2023-12-18T00:00:00.000Z",
            1
        ],
        [
            "2024-02-21T00:00:00.000Z",
            1
        ],
        [
            "2024-02-22T00:00:00.000Z",
            1
        ]
    ]
}